Metadata-Version: 2.1
Name: basicreadme
Version: 1.0.0
Summary: basic
Home-page: UNKNOWN
Author: saurabh
License: MIT
Platform: UNKNOWN
License-File: LICENCE.txt
